organisationsnummer/__init__.py
organisationsnummer/main.py
organisationsnummer/organisationsnummer.py
organisationsnummer/tests/__init__.py
organisationsnummer/tests/test_organisationsnummer.py
organisationsnummer-1.0.1.dist-info/licenses/LICENSE
organisationsnummer-1.0.1.dist-info/METADATA
organisationsnummer-1.0.1.dist-info/WHEEL
organisationsnummer-1.0.1.dist-info/entry_points.txt
organisationsnummer-1.0.1.dist-info/top_level.txt
organisationsnummer-1.0.1.dist-info/RECORD
