Metadata-Version: 2.4
Name: organisationsnummer
Version: 1.0.1
Summary: Validate Swedish organization numbers
Author-email: Organisationsnummer and Contributors <hello@organisationsnummer.dev>
License: MIT License
Project-URL: Homepage, https://organisationsnummer.dev
Project-URL: Repository, https://github.com/organisationsnummer/python
Classifier: License :: OSI Approved :: MIT License
License-File: LICENSE
Requires-Dist: personnummer
Provides-Extra: dev
Requires-Dist: pytest; extra == "dev"
Requires-Dist: build; extra == "dev"
Dynamic: license-file
